examples/__init__.py
examples/databricks/__init__.py
examples/databricks/transactions/__init__.py
examples/databricks/transactions/bronze/__init__.py
examples/databricks/transactions/bronze/nb_ingest_raw_customers.py
examples/databricks/transactions/bronze/nb_ingest_raw_transactions.py
examples/databricks/transactions/bronze/schemas/__init__.py
examples/databricks/transactions/bronze/schemas/raw_customers.py
examples/databricks/transactions/bronze/schemas/raw_transactions.py
examples/databricks/transactions/silver/__init__.py
examples/databricks/transactions/silver/nb_clean_transactions.py
examples/databricks/transactions/silver/nb_create_customer_summary.py
examples/databricks/transactions/silver/schemas/__init__.py
examples/databricks/transactions/silver/schemas/clean_transactions.py
examples/databricks/transactions/silver/schemas/customer_summary.py
jorvik/__init__.py
jorvik/version.py
jorvik/audit/__init__.py
jorvik/audit/schemas.py
jorvik/data_lineage/__init__.py
jorvik/data_lineage/execution_plan.py
jorvik/data_lineage/node_handler.py
jorvik/data_lineage/observer.py
jorvik/pipelines/__init__.py
jorvik/pipelines/etl.py
jorvik/pipelines/testing.py
jorvik/storage/__init__.py
jorvik/storage/basic.py
jorvik/storage/isolation.py
jorvik/storage/isolation_providers.py
jorvik/storage/protocols.py
jorvik/utils/__init__.py
jorvik/utils/databricks.py
jorvik/utils/git.py
jorvik/utils/paths.py
jorvik-1.2.4.data/data/requirements.txt
jorvik-1.2.4.dist-info/licenses/LICENSE
jorvik-1.2.4.dist-info/METADATA
jorvik-1.2.4.dist-info/WHEEL
jorvik-1.2.4.dist-info/top_level.txt
jorvik-1.2.4.dist-info/RECORD
