Metadata-Version: 2.4
Name: jorvik
Version: 1.2.4
Summary: A set of utilities for creating and managing ETL Pipelines with pyspark.
Home-page: https://github.com/jorvik-io/jorvik
Author: https://github.com/jorvik-io
License: Apache License 2.0
Keywords: ETL,Pyspark,Data Engineering,Data Pipelines
License-File: LICENSE
Requires-Dist: buildtools
Requires-Dist: delta-spark
Requires-Dist: pandas
Requires-Dist: pyarrow
Requires-Dist: pyspark
Provides-Extra: tests
Requires-Dist: pytest; extra == "tests"
Requires-Dist: flake8; extra == "tests"
Requires-Dist: pytest-mock; extra == "tests"
Requires-Dist: numpy<2.0.0; extra == "tests"
Dynamic: author
Dynamic: description
Dynamic: description-content-type
Dynamic: home-page
Dynamic: keywords
Dynamic: license
Dynamic: license-file
Dynamic: provides-extra
Dynamic: requires-dist
Dynamic: summary
